{"url":"https://csunibo.github.io/programmazione/esercizi/laboratorio/04","name":"04","path":"esercizi/laboratorio/04","directories":null,"files":[{"url":"https://csunibo.github.io/programmazione/esercizi/laboratorio/04/02.cpp","mime":"text/plain; charset=utf-8","name":"02.cpp","path":"esercizi/laboratorio/04/02.cpp"},{"url":"https://csunibo.github.io/programmazione/esercizi/laboratorio/04/04.cpp","mime":"text/plain; charset=utf-8","name":"04.cpp","path":"esercizi/laboratorio/04/04.cpp"},{"url":"https://csunibo.github.io/programmazione/esercizi/laboratorio/04/06.cpp","mime":"text/plain; charset=utf-8","name":"06.cpp","path":"esercizi/laboratorio/04/06.cpp"},{"url":"https://csunibo.github.io/programmazione/esercizi/laboratorio/04/08.cpp","mime":"text/plain; charset=utf-8","name":"08.cpp","path":"esercizi/laboratorio/04/08.cpp"},{"url":"https://csunibo.github.io/programmazione/esercizi/laboratorio/04/10.cpp","mime":"text/plain; charset=utf-8","name":"10.cpp","path":"esercizi/laboratorio/04/10.cpp"},{"url":"https://csunibo.github.io/programmazione/esercizi/laboratorio/04/13.cpp","mime":"text/plain; charset=utf-8","name":"13.cpp","path":"esercizi/laboratorio/04/13.cpp"},{"url":"https://csunibo.github.io/programmazione/esercizi/laboratorio/04/15.cpp","mime":"text/plain; charset=utf-8","name":"15.cpp","path":"esercizi/laboratorio/04/15.cpp"},{"url":"https://csunibo.github.io/programmazione/esercizi/laboratorio/04/17.cpp","mime":"text/plain; charset=utf-8","name":"17.cpp","path":"esercizi/laboratorio/04/17.cpp"},{"url":"https://csunibo.github.io/programmazione/esercizi/laboratorio/04/19.cpp","mime":"text/plain; charset=utf-8","name":"19.cpp","path":"esercizi/laboratorio/04/19.cpp"},{"url":"https://csunibo.github.io/programmazione/esercizi/laboratorio/04/21.cpp","mime":"text/plain; charset=utf-8","name":"21.cpp","path":"esercizi/laboratorio/04/21.cpp"}],"size":"4.1 kB","time":"2022-06-20T14:23:52.232981406Z"}